marketorestclientpython/__init__.py
marketorestclientpython/client.py
marketorestclientpython/helper/__init__.py
marketorestclientpython/helper/exceptions.py
marketorestclientpython/helper/http_lib.py
marketorestclientpython-0.3.dist-info/LICENSE.txt
marketorestclientpython-0.3.dist-info/METADATA
marketorestclientpython-0.3.dist-info/WHEEL
marketorestclientpython-0.3.dist-info/top_level.txt
marketorestclientpython-0.3.dist-info/RECORD
