Metadata-Version: 2.1
Name: marketorestclientpython
Version: 0.3
Summary: Python Client for the Marketo REST API
Home-page: UNKNOWN
Author: BackendTeam
Author-email: back@team.com
License: UNKNOWN
Keywords: Marketo,REST API,Wrapper,Client
Platform: UNKNOWN
Requires-Dist: requests
